zdpapi_elastic_search/__init__.py
zdpapi_elastic_search/object.py
zdpapi_elastic_search-1.0.0.dist-info/LICENSE
zdpapi_elastic_search-1.0.0.dist-info/WHEEL
zdpapi_elastic_search-1.0.0.dist-info/METADATA
zdpapi_elastic_search-1.0.0.dist-info/RECORD
