Metadata-Version: 2.1
Name: zdpapi-elastic-search
Version: 1.0.0
Summary: python操作ElasticSearch的基础组件
Home-page: https://github.com/zhangdapeng520/zdpapi_elastic_search
License: MIT
Keywords: zapi,ElasticSearch,search,zhangdapeng
Author: 张大鹏
Author-email: lxgzhw@163.com
Requires-Python: >=3.8,<4.0
Classifier: License :: OSI Approved :: MIT License
Classifier: Programming Language :: Python :: 3
Classifier: Programming Language :: Python :: 3.8
Classifier: Programming Language :: Python :: 3.9
Requires-Dist: elasticsearch (>=7.15.2,<8.0.0)
Project-URL: Documentation, https://github.com/zhangdapeng520/zdpapi_elastic_search
Project-URL: Repository, https://github.com/zhangdapeng520/zdpapi_elastic_search
